MANIFEST.in
README.md
setup.py
facenet/__init__.py
facenet/crop/__init__.py
facenet/crop/crop_dataset_mtcnn.py
facenet/crop/detect_face.py
facenet/crop/model/det1.npy
facenet/crop/model/det2.npy
facenet/crop/model/det3.npy
facenet/model/__init__.py
facenet/model/embeddings.py
facenet/model/facenet_model.py
facenet/utils/__init__.py
facenet/utils/utils.py
yale_dhlab_facenet.egg-info/PKG-INFO
yale_dhlab_facenet.egg-info/SOURCES.txt
yale_dhlab_facenet.egg-info/dependency_links.txt
yale_dhlab_facenet.egg-info/requires.txt
yale_dhlab_facenet.egg-info/top_level.txt