Metadata-Version: 1.0
Name: yale-dhlab-facenet
Version: 0.0.2
Summary: Python implementation of the facenet model
Home-page: https://github.com/yaledhlab/yale-facenet
Author: David Sandberg, packaged by Douglas Duhaime
Author-email: douglas.duhaime@gmail.com
License: MIT
Keywords: machine-learning,tensorflow,facenet,computer-vision
Platform: UNKNOWN
